{
  "_id": "BsUGkg9fU3BdnYXm",
  "name": "Spellcaster (Warp)",
  "permission": {
    "default": 0,
    "LhiA8OMMa0ToAWEe": 3
  },
  "type": "trait",
  "data": {
    "description": {
      "type": "String",
      "label": "Description",
      "value": "<p>You gain the Chaos Magic (Warp) and Petty Magic Talents plus a number of spells determined by the GM, as appropriate to the character.</p>"
    },
    "gmdescription": {
      "type": "String",
      "label": "Description",
      "value": ""
    },
    "rollable": {
      "value": false,
      "label": "Rollable",
      "type": "Boolean",
      "rollCharacteristic": "",
      "bonusCharacteristic": "",
      "defaultDifficulty": "challenging"
    },
    "specification": {
      "value": "",
      "type": "String",
      "label": "Specification"
    }
  },
  "flags": {
    "core": {
      "sourceId": "Item.mqU8WupJng2dbqmF"
    }
  },
  "img": "systems/wfrp4e/icons/blank.png",
  "effects": [],
  "_key": "!items!BsUGkg9fU3BdnYXm"
}
