{
  "name": "Strzaskana Czaszka",
  "type": "critical",
  "img": "modules/wfrp4e-core/icons/injuries/head.png",
  "effects": [
    {
      "label": "Strzaskana Czaszka",
      "icon": "modules/wfrp4e-core/icons/injuries/head.png",
      "transfer": true,
      "_id": "mnboGn92eHPGUb1D",
      "changes": [],
      "disabled": false,
      "duration": {
        "startTime": null,
        "seconds": null,
        "combat": null,
        "rounds": null,
        "turns": null,
        "startRound": null,
        "startTurn": null
      },
      "origin": null,
      "tint": null,
      "flags": {
        "wfrp4e": {
          "effectTrigger": "oneTime",
          "effectApplication": "actor",
          "hide": false,
          "preventDuplicateEffects": false,
          "script": "await this.actor.addCondition(\"dead\");"
        }
      },
      "_key": "!items.effects!P95OD8IMBWBWWBS3.mnboGn92eHPGUb1D"
    }
  ],
  "flags": {
    "core": {
      "sourceId": "Compendium.wfrp4e-pl.criticals.P95OD8IMBWBWWBS3"
    }
  },
  "system": {
    "description": {
      "type": "String",
      "label": "Description",
      "value": "<p>Twoja głowa pęka niczym arbuz. Martwe, bezgłowe ciało pada na ziemię.</p>"
    },
    "gmdescription": {
      "type": "String",
      "label": "Description",
      "value": ""
    },
    "wounds": {
      "value": "Death",
      "type": "String",
      "label": "Wounds"
    },
    "modifier": {
      "value": "",
      "type": "String",
      "label": "Test Modifier"
    },
    "location": {
      "value": "Głowa",
      "type": "String",
      "label": "Location"
    }
  },
  "folder": null,
  "sort": 0,
  "_id": "P95OD8IMBWBWWBS3",
  "_key": "!items!P95OD8IMBWBWWBS3"
}
