{
  "name": "Leyfinding",
  "system": {
    "description": {
      "type": "String",
      "label": "Description",
      "value": "<p>Tapping into the flows of earthbound magic, you receive a detailed mental map of all leylines and stone circles within range. This knowledge provides +2 SL to Navigation Tests made to locate planned or natural leylines. You cannot discern specific colours of magic from afar, but you can sense each leyline’s overall strength (minor or major), along with the number of waystones in every stone circle. See @UUID[JournalEntry.BBMts94CJGZ3wRMi]{The Winds at Work} for more on leylines and waystones.</p><p><strong>Lore:</strong> Receive a +10 bonus to Casting and Channeling rolls when in a rural or wilderness environment. Living creatures — e.g. those without the @UUID[Compendium.wfrp4e-core.items.v3uzEthcq0JRar0J]{Daemonic} or @UUID[Compendium.wfrp4e-core.items.PFTD9gDvRWW9uh5g]{Undead} Creature Traits — targeted by Arcane Spells from the Lore of Life have all @Condition[Fatigued] and @Condition[Bleeding] Conditions removed after any other effects have been applied as life magic floods through them. Creatures with the @UUID[Compendium.wfrp4e-core.items.PFTD9gDvRWW9uh5g]{Undead} Creature Trait, on the other hand, suffer additional Damage equal to your Willpower Bonus, ignoring Toughness Bonus and Armor Points, if affected by any spell cast with the Lore of Life.</p><p></p>"
    },
    "gmdescription": {
      "type": "String",
      "label": "Description",
      "value": ""
    },
    "lore": {
      "type": "String",
      "label": "Lore",
      "value": "life",
      "effectString": "",
      "effect": ""
    },
    "range": {
      "type": "String",
      "label": "Range",
      "value": "Initiative Bonus miles",
      "vortex": false
    },
    "target": {
      "type": "String",
      "label": "Target",
      "value": "You",
      "aoe": false
    },
    "duration": {
      "type": "String",
      "label": "Duration",
      "value": "Willpower Bonus hours",
      "extendable": false
    },
    "damage": {
      "type": "String",
      "label": "Damage",
      "dice": "",
      "value": ""
    },
    "cn": {
      "type": "Number",
      "label": "Casting Number",
      "value": 5,
      "SL": 0
    },
    "magicMissile": {
      "type": "Boolean",
      "label": "Magic Missile",
      "value": false
    },
    "ritual": {
      "value": false,
      "type": "",
      "xp": 0
    },
    "memorized": {
      "type": "Boolean",
      "label": "Memorized",
      "value": false
    },
    "skill": {
      "value": ""
    },
    "ingredients": [],
    "currentIng": {
      "type": "Number",
      "label": "Ingredient",
      "value": ""
    },
    "wind": {
      "value": ""
    },
    "overcast": {
      "enabled": false,
      "label": "",
      "valuePerOvercast": {
        "type": "",
        "value": 1,
        "SL": false,
        "characteristic": "",
        "bonus": false
      },
      "initial": {
        "type": "",
        "value": 1,
        "SL": false,
        "characteristic": "",
        "bonus": false
      }
    }
  },
  "type": "spell",
  "folder": "O2HAVLlkGzyX0NIV",
  "img": "modules/wfrp4e-core/icons/spells/life.png",
  "effects": [
    {
      "icon": "modules/wfrp4e-core/icons/spells/life.png",
      "transfer": false,
      "_id": "GrBYWxHsSus7jnPG",
      "changes": [],
      "disabled": false,
      "duration": {
        "startTime": null,
        "seconds": null,
        "combat": null,
        "rounds": null,
        "turns": null,
        "startRound": null,
        "startTurn": null
      },
      "origin": null,
      "tint": null,
      "flags": {
        "wfrp4e": {
          "effectTrigger": "dialogChoice",
          "effectApplication": "apply",
          "hide": false,
          "preventDuplicateEffects": false,
          "effectData": {
            "description": "Navigation to find leylines",
            "modifier": null,
            "slBonus": 2,
            "successBonus": null,
            "difficultyStep": null
          }
        }
      },
      "name": "Leyfinding",
      "description": "",
      "statuses": [],
      "_key": "!items.effects!S548dPRBpyJRnKCI.GrBYWxHsSus7jnPG"
    }
  ],
  "sort": 0,
  "ownership": {
    "default": 0,
    "Oxrm36DvLya7eQ7D": 3
  },
  "flags": {
    "wfrp4e-wom": {
      "initialization-folder": "Life",
      "sort": 0
    }
  },
  "_stats": {
    "systemId": "wfrp4e",
    "systemVersion": "7.0.0",
    "coreVersion": "11.307",
    "createdTime": 1676322951221,
    "modifiedTime": 1693273575734,
    "lastModifiedBy": "sAiwDCZFd21tgaDN"
  },
  "_id": "S548dPRBpyJRnKCI",
  "_key": "!items!S548dPRBpyJRnKCI"
}
