{
  "name": "Mindslip",
  "system": {
    "description": {
      "type": "String",
      "label": "Description",
      "value": "<p>You conjure delicate threads of <em>Ulgu</em> in your target’s mind, causing all prior memory of you to disappear for the spell’s duration. Once the spell is over, the target must pass an <strong>Average (+20) Intelligence</strong> Test, or the memory loss becomes permanent until dispelled.</p><p><strong>Lore:</strong> All spells cast from the Lore of Shadows inflicting Damage ignore all non-magical Armor Points.</p><p></p>"
    },
    "gmdescription": {
      "type": "String",
      "label": "Description",
      "value": ""
    },
    "lore": {
      "type": "String",
      "label": "Lore",
      "value": "shadow",
      "effectString": "",
      "effect": ""
    },
    "range": {
      "type": "String",
      "label": "Range",
      "value": "1 yard",
      "vortex": false
    },
    "target": {
      "type": "String",
      "label": "Target",
      "value": "1",
      "aoe": false
    },
    "duration": {
      "type": "String",
      "label": "Duration",
      "value": "Willpower minutes",
      "extendable": false
    },
    "damage": {
      "type": "String",
      "label": "Damage",
      "dice": "",
      "value": ""
    },
    "cn": {
      "type": "Number",
      "label": "Casting Number",
      "value": 6,
      "SL": 0
    },
    "magicMissile": {
      "type": "Boolean",
      "label": "Magic Missile",
      "value": false
    },
    "ritual": {
      "value": false,
      "type": "",
      "xp": 0
    },
    "memorized": {
      "type": "Boolean",
      "label": "Memorized",
      "value": false
    },
    "skill": {
      "value": ""
    },
    "ingredients": [],
    "currentIng": {
      "type": "Number",
      "label": "Ingredient",
      "value": ""
    },
    "wind": {
      "value": ""
    },
    "overcast": {
      "enabled": false,
      "label": "",
      "valuePerOvercast": {
        "type": "",
        "value": 1,
        "SL": false,
        "characteristic": "",
        "bonus": false
      },
      "initial": {
        "type": "",
        "value": 1,
        "SL": false,
        "characteristic": "",
        "bonus": false
      }
    }
  },
  "type": "spell",
  "folder": "wxBwSMVLtd5DgtDb",
  "img": "modules/wfrp4e-core/icons/spells/mindslip.png",
  "effects": [],
  "sort": 0,
  "ownership": {
    "default": 0,
    "Oxrm36DvLya7eQ7D": 3
  },
  "flags": {
    "wfrp4e-wom": {
      "initialization-folder": "Shadow",
      "sort": 0
    }
  },
  "_stats": {
    "systemId": "wfrp4e",
    "systemVersion": "7.0.0",
    "coreVersion": "11.307",
    "createdTime": 1676402587846,
    "modifiedTime": 1693273575746,
    "lastModifiedBy": "sAiwDCZFd21tgaDN"
  },
  "_id": "WagjYxg0wxxwCpQB",
  "_key": "!items!WagjYxg0wxxwCpQB"
}
