{
  "_id": "mrEqBx1aCCdnQ3Qn",
  "name": "Curse of the Horned One",
  "permission": {
    "default": 0,
    "LhiA8OMMa0ToAWEe": 3
  },
  "type": "spell",
  "data": {
    "description": {
      "type": "String",
      "label": "Description",
      "value": "<p>Known as <em>The Dreaded Thirteenth Spell</em> for unknown reasons, you mutate your target into the form of a Skaven, who is allowed an <strong>Impossible (-50) Cool</strong> Test to resist. If failed, your target is totally under your influence and will do whatever they are told (except for directly killing themselves). The target maintains their characteristics but adds the basic Clanrat Creature Traits. When the spell ends, the target must pass a <strong>Challenging (+0) Endurance</strong> Test to survive the transformation unharmed. If the Test is failed, the victim takes 2d10 Damage ignoring Armour (minimum of 1). If the Test is Fumbled, the target suﬀers a Critical Hit, adding +60 to the roll on the Critical Table.</p>"
    },
    "gmdescription": {
      "type": "String",
      "label": "Description",
      "value": ""
    },
    "lore": {
      "type": "String",
      "label": "Lore",
      "value": "Warp",
      "effect": "Warp Sorcerers gain a +10 bonus to Channelling and Language (Magick) Tests in any underground environment, such as a cavern, sewer or even a basement. Targets who suﬀer Wounds from Warp Lore spells must pass an Average (+20) Endurance Test to avoid contracting a Minor Infection."
    },
    "range": {
      "type": "String",
      "label": "Range",
      "value": "Touch"
    },
    "target": {
      "type": "String",
      "label": "Target",
      "value": "1",
      "aoe": false
    },
    "duration": {
      "type": "String",
      "label": "Duration",
      "value": "Willpower hours",
      "extendable": false
    },
    "damage": {
      "type": "String",
      "label": "Damage",
      "value": ""
    },
    "cn": {
      "type": "Number",
      "label": "Casting Number",
      "value": 13,
      "SL": 0
    },
    "magicMissile": {
      "type": "Boolean",
      "label": "Magic Missile",
      "value": false
    },
    "memorized": {
      "type": "Boolean",
      "label": "Memorized",
      "value": false
    },
    "ingredients": [],
    "currentIng": {
      "type": "Number",
      "label": "Ingredient",
      "value": 0
    },
    "wind": {
      "value": ""
    }
  },
  "flags": {
    "core": {
      "sourceId": "Item.EBwHjtOBsIF7dzdQ"
    }
  },
  "img": "modules/wfrp4e-unofficial-grimoire/icons/spell_curse%20of%20the%20horned%20one.jpg",
  "effects": [],
  "_key": "!items!mrEqBx1aCCdnQ3Qn"
}
